<?xml version="1.0"?>
<Runs Version="1" Minor="0">
	<Run Id="embsys_ila_0_0_synth_1" LaunchDir="C:/Users/ME/Vivado_Projects/project_2/project_2.runs/embsys_ila_0_0_synth_1" FlowId="Vivado_Synthesis" FromStepId="vivado" ToStepId="vivado"/>
	<Run Id="embsys_nexys4IO_0_1_synth_1" LaunchDir="C:/Users/ME/Vivado_Projects/project_2/project_2.runs/embsys_nexys4IO_0_1_synth_1" FlowId="Vivado_Synthesis" FromStepId="vivado" ToStepId="vivado"/>
	<Run Id="embsys_PmodOLEDrgb_0_1_synth_1" LaunchDir="C:/Users/ME/Vivado_Projects/project_2/project_2.runs/embsys_PmodOLEDrgb_0_1_synth_1" FlowId="Vivado_Synthesis" FromStepId="vivado" ToStepId="vivado"/>
	<Run Id="embsys_fit_timer_0_1_synth_1" LaunchDir="C:/Users/ME/Vivado_Projects/project_2/project_2.runs/embsys_fit_timer_0_1_synth_1" FlowId="Vivado_Synthesis" FromStepId="vivado" ToStepId="vivado"/>
	<Run Id="embsys_mdm_1_1_synth_1" LaunchDir="C:/Users/ME/Vivado_Projects/project_2/project_2.runs/embsys_mdm_1_1_synth_1" FlowId="Vivado_Synthesis" FromStepId="vivado" ToStepId="vivado"/>
	<Run Id="embsys_clk_wiz_1_1_synth_1" LaunchDir="C:/Users/ME/Vivado_Projects/project_2/project_2.runs/embsys_clk_wiz_1_1_synth_1" FlowId="Vivado_Synthesis" FromStepId="vivado" ToStepId="vivado"/>
	<Run Id="embsys_dlmb_v10_1_synth_1" LaunchDir="C:/Users/ME/Vivado_Projects/project_2/project_2.runs/embsys_dlmb_v10_1_synth_1" FlowId="Vivado_Synthesis" FromStepId="vivado" ToStepId="vivado"/>
	<Run Id="embsys_ilmb_v10_1_synth_1" LaunchDir="C:/Users/ME/Vivado_Projects/project_2/project_2.runs/embsys_ilmb_v10_1_synth_1" FlowId="Vivado_Synthesis" FromStepId="vivado" ToStepId="vivado" IsOrderedIPRun="true">
		<Parent Id="embsys_dlmb_v10_1_synth_1"/>
	</Run>
	<Run Id="embsys_ilmb_bram_if_cntlr_1_synth_1" LaunchDir="C:/Users/ME/Vivado_Projects/project_2/project_2.runs/embsys_ilmb_bram_if_cntlr_1_synth_1" FlowId="Vivado_Synthesis" FromStepId="vivado" ToStepId="vivado"/>
	<Run Id="embsys_lmb_bram_1_synth_1" LaunchDir="C:/Users/ME/Vivado_Projects/project_2/project_2.runs/embsys_lmb_bram_1_synth_1" FlowId="Vivado_Synthesis" FromStepId="vivado" ToStepId="vivado"/>
	<Run Id="embsys_PmodENC_0_1_synth_1" LaunchDir="C:/Users/ME/Vivado_Projects/project_2/project_2.runs/embsys_PmodENC_0_1_synth_1" FlowId="Vivado_Synthesis" FromStepId="vivado" ToStepId="vivado"/>
	<Run Id="synth_1" LaunchDir="C:/Users/ME/Vivado_Projects/project_2/project_2.runs/synth_1" FlowId="Vivado_Synthesis" FromStepId="vivado" ToStepId="vivado">
		<Parent Id="embsys_ila_0_0_synth_1"/>
		<Parent Id="embsys_nexys4IO_0_1_synth_1"/>
		<Parent Id="embsys_PmodOLEDrgb_0_1_synth_1"/>
		<Parent Id="embsys_fit_timer_0_1_synth_1"/>
		<Parent Id="embsys_mdm_1_1_synth_1"/>
		<Parent Id="embsys_clk_wiz_1_1_synth_1"/>
		<Parent Id="embsys_dlmb_v10_1_synth_1"/>
		<Parent Id="embsys_ilmb_v10_1_synth_1"/>
		<Parent Id="embsys_ilmb_bram_if_cntlr_1_synth_1"/>
		<Parent Id="embsys_lmb_bram_1_synth_1"/>
		<Parent Id="embsys_PmodENC_0_1_synth_1"/>
	</Run>
	<Run Id="impl_1" LaunchDir="C:/Users/ME/Vivado_Projects/project_2/project_2.runs/impl_1" FlowId="Vivado_Implementation" FromStepId="init_design" ToStepId="write_bitstream">
		<Parent Id="synth_1"/>
		<Parent Id="embsys_ila_0_0_synth_1"/>
		<Parent Id="embsys_nexys4IO_0_1_synth_1"/>
		<Parent Id="embsys_PmodOLEDrgb_0_1_synth_1"/>
		<Parent Id="embsys_fit_timer_0_1_synth_1"/>
		<Parent Id="embsys_mdm_1_1_synth_1"/>
		<Parent Id="embsys_clk_wiz_1_1_synth_1"/>
		<Parent Id="embsys_dlmb_v10_1_synth_1"/>
		<Parent Id="embsys_ilmb_v10_1_synth_1"/>
		<Parent Id="embsys_ilmb_bram_if_cntlr_1_synth_1"/>
		<Parent Id="embsys_lmb_bram_1_synth_1"/>
		<Parent Id="embsys_PmodENC_0_1_synth_1"/>
	</Run>
</Runs>

